breakthecode/__init__.py
breakthecode/__main__.py
breakthecode/cli.py
breakthecode/constraints.py
breakthecode/model.py
breakthecode-1.0.0.dist-info/LICENSE
breakthecode-1.0.0.dist-info/METADATA
breakthecode-1.0.0.dist-info/WHEEL
breakthecode-1.0.0.dist-info/entry_points.txt
breakthecode-1.0.0.dist-info/top_level.txt
breakthecode-1.0.0.dist-info/RECORD
