Metadata-Version: 2.1
Name: breakthecode
Version: 1.0.0
Summary: BreakTheCode board game helper
Home-page: https://github.com/dynod/breakthecode
Author: The dynod project
Maintainer: The dynod project
License: Mozilla Public License Version 2.0
Platform: UNKNOWN
Classifier: Programming Language :: Python :: 3.8
Classifier: Programming Language :: Python :: 3.9
Classifier: Programming Language :: Python :: 3.10
Requires-Dist: rich
Requires-Dist: argcomplete
